MANIFEST.in
setup.cfg
setup.py
tw/__init__.py
tw.timeline.egg-info/PKG-INFO
tw.timeline.egg-info/SOURCES.txt
tw.timeline.egg-info/dependency_links.txt
tw.timeline.egg-info/entry_points.txt
tw.timeline.egg-info/namespace_packages.txt
tw.timeline.egg-info/not-zip-safe
tw.timeline.egg-info/requires.txt
tw.timeline.egg-info/top_level.txt
tw/timeline/__init__.py
tw/timeline/base.py
tw/timeline/defaults.py
tw/timeline/release.py
tw/timeline/samples.py
tw/timeline/timeline.py
tw/timeline/widgets.py
tw/timeline/static/__init__.py
tw/timeline/static/__init__.pyc
tw/timeline/static/2.2.0/__init__.py
tw/timeline/static/2.2.0/demo.js
tw/timeline/static/2.2.0/api/timeline-api.js
tw/timeline/static/2.2.0/api/timeline-bundle.css
tw/timeline/static/2.2.0/api/timeline-bundle.js
tw/timeline/static/2.2.0/api/ext/geochrono/geochrono-api.js
tw/timeline/static/2.2.0/api/ext/geochrono/scripts/ether-painters.js
tw/timeline/static/2.2.0/api/ext/geochrono/scripts/geochrono.js
tw/timeline/static/2.2.0/api/ext/geochrono/scripts/labellers.js
tw/timeline/static/2.2.0/api/ext/geochrono/scripts/units.js
tw/timeline/static/2.2.0/api/ext/geochrono/scripts/l10n/en/labellers.js
tw/timeline/static/2.2.0/api/ext/planning/planning-api.js
tw/timeline/static/2.2.0/api/ext/planning/scripts/ether-painters.js
tw/timeline/static/2.2.0/api/ext/planning/scripts/labellers.js
tw/timeline/static/2.2.0/api/ext/planning/scripts/planning.js
tw/timeline/static/2.2.0/api/ext/planning/scripts/units.js
tw/timeline/static/2.2.0/api/ext/planning/scripts/l10n/en/labellers.js
tw/timeline/static/2.2.0/api/images/blue-circle.png
tw/timeline/static/2.2.0/api/images/bubble-bottom-arrow.png
tw/timeline/static/2.2.0/api/images/bubble-bottom-left.png
tw/timeline/static/2.2.0/api/images/bubble-bottom-right.png
tw/timeline/static/2.2.0/api/images/bubble-bottom.png
tw/timeline/static/2.2.0/api/images/bubble-left-arrow.png
tw/timeline/static/2.2.0/api/images/bubble-left.png
tw/timeline/static/2.2.0/api/images/bubble-right-arrow.png
tw/timeline/static/2.2.0/api/images/bubble-right.png
tw/timeline/static/2.2.0/api/images/bubble-top-arrow.png
tw/timeline/static/2.2.0/api/images/bubble-top-left.png
tw/timeline/static/2.2.0/api/images/bubble-top-right.png
tw/timeline/static/2.2.0/api/images/bubble-top.png
